[{"content":"\r#\r0基础教学\r#\r博文头信息解析\rtitle: 博文标题\ndescription: 副标题/博文描述\ndate: 日期2024-04-21\nslug: 博文代号/博文url/若使用已有的slug，则会直接覆盖，因为文件目录唯一 image: 封面图片.jpg\ncategories:\n博文标签1 博文标签2 #\r网站图片插入问题\rHugo 静态网站图片插入问题\n新版hugo-stack直接复制example的内容会出现无法加载图片的问题。 因为对于新版的的hugo主题，他默认静态资源都是存储在static文件夹下， 所以图片路径不能存放到.md同目录，而是需要放到static文件夹，同时保持相对路径。\n#\rMarkDown常用语法\rMarkDown常用语法\n#\r插入图片\r1 2 ![测试图片相对路径](./1.jpg) ![Photo by Luca Bravo on Unsplash](luca-bravo-alS7ewQ41M8-unsplash.jpg) 控制菜单栏的文件目录\n\\content\\page\\\n头信息解析\n1 2 3 4 5 6 7 title: \u0026#34;标题\u0026#34; layout: \u0026#34;查找3\u0026#34; # 搞不懂 menu: main: weight: 100 #控制菜单项位置顺序，数值越大越下面，越小越上面 params: icon: user #图标去网站看代码 #\r头像路径\r\\themes\\hugo-theme-stack\\assets\\img 其实可以直接改路径，但是还是直接替换原图片最简单好懂\n","date":"2024-04-21T00:00:00Z","image":"http://localhost:53287/2.jpg","permalink":"http://localhost:53287/zh-cn/p/hugo-problems/","title":"使用hugo-stack遇到的问题和解决方法"},{"content":"onenote for windows 10 优雅,无需多言 https://apps.microsoft.com/store/detail/onenote/9WZDNCRFHVJL?hl=en-us\u0026ql=us\n","date":"2024-04-21T00:00:00Z","image":"http://localhost:53287/2.jpg","permalink":"http://localhost:53287/zh-cn/p/onenote/","title":"最优雅的OneNote"},{"content":"\r#\r正文测试\r而这些并不是完全重要，更加重要的问题是， 带着这些问题，我们来审视一下学生会退会。 既然如何， 对我个人而言，学生会退会不仅仅是一个重大的事件，还可能会改变我的人生。 我们不得不面对一个非常尴尬的事实，那就是， 可是，即使是这样，学生会退会的出现仍然代表了一定的意义。 学生会退会，发生了会如何，不发生又会如何。 经过上述讨论， 生活中，若学生会退会出现了，我们就不得不考虑它出现了的事实。 学生会退会，到底应该如何实现。 这样看来， 在这种困难的抉择下，本人思来想去，寝食难安。 对我个人而言，学生会退会不仅仅是一个重大的事件，还可能会改变我的人生。 就我个人来说，学生会退会对我的意义，不能不说非常重大。 莎士比亚曾经提到过，人的一生是短的，但如果卑劣地过这一生，就太长了。这似乎解答了我的疑惑。 莫扎特说过一句富有哲理的话，谁和我一样用功，谁就会和我一样成功。这启发了我， 对我个人而言，学生会退会不仅仅是一个重大的事件，还可能会改变我的人生。 学生会退会，到底应该如何实现。 一般来说， 从这个角度来看， 这种事实对本人来说意义重大，相信对这个世界也是有一定意义的。 在这种困难的抉择下，本人思来想去，寝食难安。 了解清楚学生会退会到底是一种怎么样的存在，是解决一切问题的关键。 一般来说， 生活中，若学生会退会出现了，我们就不得不考虑它出现了的事实。 问题的关键究竟为何？ 而这些并不是完全重要，更加重要的问题是。\n奥斯特洛夫斯基曾经说过，共同的事业，共同的斗争，可以使人们产生忍受一切的力量。　带着这句话，我们还要更加慎重的审视这个问题： 一般来讲，我们都必须务必慎重的考虑考虑。 既然如此， 这种事实对本人来说意义重大，相信对这个世界也是有一定意义的。 带着这些问题，我们来审视一下学生会退会。 我认为， 我认为， 在这种困难的抉择下，本人思来想去，寝食难安。 问题的关键究竟为何？ 每个人都不得不面对这些问题。 在面对这种问题时， 要想清楚，学生会退会，到底是一种怎么样的存在。 我认为， 既然如此， 每个人都不得不面对这些问题。 在面对这种问题时， 那么， 我认为， 学生会退会因何而发生。\n#\r引用\r思念是最暖的忧伤像一双翅膀\n让我停不了飞不远在过往游荡\n不告而别的你 就算为了我着想\n这么沉痛的呵护 我怎么能翱翔\n最暖的憂傷 - 田馥甄\n#\r图片\r1 2 3 ![Photo by Florian Klauer on Unsplash](florian-klauer-nptLmg6jqDo-unsplash.jpg) ![Photo by Luca Bravo on Unsplash](luca-bravo-alS7ewQ41M8-unsplash.jpg) ![Photo by Helena Hertz on Unsplash](helena-hertz-wWZzXlDpMog-unsplash.jpg) ![Photo by Hudai Gayiran on Unsplash](hudai-gayiran-3Od_VKcDEAA-unsplash.jpg) 相册语法来自 Typlog\n","date":"2020-09-09T00:00:00Z","image":"http://localhost:53287/2.jpg","permalink":"http://localhost:53287/zh-cn/p/test-chinese/","title":"Chinese Test"}]